fanpoints_python/__init__.py
fanpoints_python/auth_session.py
fanpoints_python/backendConfig.py
fanpoints_python/conversion_module.py
fanpoints_python/date_utils.py
fanpoints_python/fanpoints_client.py
fanpoints_python/queries/doesUserExist.graphql
fanpoints_python/queries/estimateGivenOutFanPointsOnPurchase.graphql
fanpoints_python/queries/getFanPointsTransaction.graphql
fanpoints_python/queries/getFanPointsTransactions.graphql
fanpoints_python/queries/getPriceInFanPoints.graphql
fanpoints_python/queries/giveFanPointsOnPurchase.graphql
fanpoints_python/queries/payPurchaseWithFanPoints.graphql
fanpoints_python/queries/ping.graphql
fanpoints_python/queries/undoFanPointsTransaction.graphql
fanpoints_python/return_or_raise.py
fanpoints_python/types/__init__.py
fanpoints_python/types/async_base_client.py
fanpoints_python/types/base_model.py
fanpoints_python/types/client.py
fanpoints_python/types/does_user_exist.py
fanpoints_python/types/enums.py
fanpoints_python/types/estimate_given_out_fan_points_on_purchase.py
fanpoints_python/types/exceptions.py
fanpoints_python/types/get_fan_points_balance.py
fanpoints_python/types/get_fan_points_transaction.py
fanpoints_python/types/get_fan_points_transactions.py
fanpoints_python/types/get_price_in_fan_points.py
fanpoints_python/types/give_fan_points_on_purchase.py
fanpoints_python/types/input_types.py
fanpoints_python/types/pay_purchase_with_fan_points.py
fanpoints_python/types/ping.py
fanpoints_python/types/undo_fan_points_purchase.py
fanpoints_python/user_module.py
fanpoints_python-0.0.2.dist-info/METADATA
fanpoints_python-0.0.2.dist-info/WHEEL
fanpoints_python-0.0.2.dist-info/RECORD
